{
    "columns": [
      {
        "sorted": true,
        "caption": "Проект",
        "type": 2,
        "property": "project",
        "size": 2,
        "maskName": null,
        "mask": null,
        "mode": null,
        "fields": [],
        "columns": [],
        "actions": null,
        "commands": null,
        "orderNumber": 20,
        "required": false,
        "visibility": null,
        "enablement": null,
        "obligation": null,
        "readonly": true,
        "selectionPaginated": true,
        "validators": null,
        "hint": "",
        "historyDisplayMode": 0,
        "tags": null,
        "selConditions": [],
        "selSorting": []
      },
      {
        "sorted": true,
        "caption": "Участник",
        "type": 2,
        "property": "participant",
        "size": 2,
        "maskName": null,
        "mask": null,
        "mode": null,
        "fields": [],
        "columns": [],
        "actions": null,
        "commands": null,
        "orderNumber": 20,
        "required": false,
        "visibility": null,
        "enablement": null,
        "obligation": null,
        "readonly": true,
        "selectionPaginated": true,
        "validators": null,
        "hint": "",
        "historyDisplayMode": 0,
        "tags": null,
        "selConditions": [],
        "selSorting": []
      },
      {
        "sorted": true,
        "caption": "Занятость участника (%)",
        "type": 14,
        "property": "occupationEmployee",
        "size": 2,
        "maskName": null,
        "mask": null,
        "mode": null,
        "fields": [],
        "columns": [],
        "actions": null,
        "commands": null,
        "orderNumber": 50,
        "required": false,
        "visibility": null,
        "enablement": null,
        "obligation": null,
        "readonly": true,
        "selectionPaginated": true,
        "validators": null,
        "hint": "",
        "historyDisplayMode": 0,
        "tags": null,
        "selConditions": [],
        "selSorting": []
      }
    ],
    "actions": null,
    "allowSearch": true,
    "pageSize": null,
    "useEditModels": true,
    "version": null,
    "overrideMode": 1,
    "commands": [
      {
        "id": "CREATE",
        "caption": "Создать",
        "visibilityCondition": "",
        "enableCondition": "",
        "needSelectedItem": false,
        "signBefore": false,
        "signAfter": false,
        "isBulk": false
      },
      {
        "id": "EDIT",
        "caption": "Изменить",
        "visibilityCondition": "",
        "enableCondition": "",
        "needSelectedItem": true,
        "signBefore": false,
        "signAfter": false,
        "isBulk": false
      }
    ],
    "metaVersion": "2.0.61.18033"
  }